{
  "name": "Paul Mcgee",
  "phone": "1-604-894-0593",
  "email": "paulmcgee3853@yopmail.com",
  "address": "Ap #131-1141 A Ave",
  "postalZip": "64931",
  "region": "South Island",
  "country": "Singapore"
}{
  "name": "Vance West",
  "phone": "(170) 585-5196",
  "email": "vancewest@yopmail.com",
  "address": "Ap #534-5953 Metus Road",
  "postalZip": "21763",
  "region": "Bihar",
  "country": "Singapore"
}{
  "name": "Kimberley Phillips",
  "phone": "1-236-820-7376",
  "email": "kimberleyphillips@yopmail.com",
  "address": "455-4481 Nam St.",
  "postalZip": "34662",
  "region": "Tyumen Oblast",
  "country": "Singapore"
}{
  "name": "Lillith Sutton",
  "phone": "1-466-267-0517",
  "email": "lillithsutton@yopmail.com",
  "address": "458-5124 Integer St.",
  "postalZip": "16589",
  "region": "Marche",
  "country": "Singapore"
}{
  "name": "Sade Chaney",
  "phone": "1-253-400-0643",
  "email": "sadechaney@yopmail.com",
  "address": "Ap #785-6644 Nec Rd.",
  "postalZip": "14603",
  "region": "Murcia",
  "country": "Singapore"
}{
  "name": "Troy Jones",
  "phone": "(846) 145-5899",
  "email": "troyjones@yopmail.com",
  "address": "Ap #278-2117 Augue Rd.",
  "postalZip": "463827",
  "region": "North-East Region",
  "country": "Singapore"
}{
  "name": "Chase Winters",
  "phone": "(183) 262-6844",
  "email": "chasewinters7588@yopmail.com",
  "address": "P.O. Box 214, 7027 Cras Av.",
  "postalZip": "41813",
  "region": "Ceará",
  "country": "Singapore"
}{
  "name": "Garrison Mitchell",
  "phone": "(677) 775-5328",
  "email": "garrisonmitchell7915@yopmail.com",
  "address": "277-7222 Feugiat Rd.",
  "postalZip": "77-212",
  "region": "Central Java",
  "country": "Singapore"
}{
  "name": "Hedwig Burks",
  "phone": "1-835-634-8531",
  "email": "hedwigburks1450@yopmail.com",
  "address": "308-2018 Nec Rd.",
  "postalZip": "66-46",
  "region": "Mizoram",
  "country": "Singapore"
}